wiki_sub_scrapper
