Metadata-Version: 1.1
Name: wiki-sub-scrapper
Version: 0.0.2
Summary: Module to get all subsidiaries of the given company using wikipedia
Home-page: UNKNOWN
Author: Aswin venkat
Author-email: aswin.venkat@cybersecurityworks.com
License: MIT
Keywords: subsidiaries,wikipedia
Platform: UNKNOWN
Classifier: Development Status :: 5 - Production/Stable
Classifier: Intended Audience :: Education
Classifier: Operating System :: Microsoft :: Windows :: Windows 10
Classifier: License :: OSI Approved :: MIT License
Classifier: Programming Language :: Python :: 3
